aiokafka_service_secretaria/__init__.py
aiokafka_service_secretaria/kafka_consumer/__init__.py
aiokafka_service_secretaria/kafka_consumer/kafka_consumer.py
aiokafka_service_secretaria/kafka_producer/__init__.py
aiokafka_service_secretaria/kafka_producer/kafka_producer.py
aiokafka_service_secretaria/services/__init__.py
aiokafka_service_secretaria/services/kafka_service.py
aiokafka_service_secretaria-0.0.1.dist-info/LICENSE
aiokafka_service_secretaria-0.0.1.dist-info/METADATA
aiokafka_service_secretaria-0.0.1.dist-info/WHEEL
aiokafka_service_secretaria-0.0.1.dist-info/RECORD
