Metadata-Version: 2.1
Name: aiokafka_service_secretaria
Version: 0.0.1
Summary: aiokafka manager service for Centralita App
License: MIT
Author: Dsalme
Author-email: dsalme@gmail.com
Requires-Python: ==3.10.14
Classifier: License :: OSI Approved :: MIT License
Classifier: Programming Language :: Python :: 3
Requires-Dist: aiokafka (==0.11.0)
